beancounter/__init__.py
beancounter/cli.py
beancounter-0.1.1.dist-info/METADATA
beancounter-0.1.1.dist-info/WHEEL
beancounter-0.1.1.dist-info/entry_points.txt
beancounter-0.1.1.dist-info/RECORD
